{
  "kind": "collectionType",
  "collectionName": "contents",
  "info": {
    "singularName": "content",
    "pluralName": "contents",
    "displayName": "Content"
  },
  "options": {
    "draftAndPublish": true
  },
  "pluginOptions": {},
  "attributes": {
    "title": {
      "type": "string"
    },
    "description": {
      "type": "blocks"
    },
    "video": {
      "allowedTypes": [
        "files",
        "videos"
      ],
      "type": "media",
      "multiple": true
    },
    "image": {
      "allowedTypes": [
        "images"
      ],
      "type": "media",
      "multiple": true
    },
    "embedContent": {
      "type": "string"
    }
  }
}
